mehrshad/__init__.py
mehrshad/excel.py
mehrshad/fileManage.py
mehrshad/pygameFunctions.py
mehrshad-0.4b0.dist-info/LICENSE
mehrshad-0.4b0.dist-info/METADATA
mehrshad-0.4b0.dist-info/WHEEL
mehrshad-0.4b0.dist-info/top_level.txt
mehrshad-0.4b0.dist-info/RECORD
