Metadata-Version: 2.1
Name: mehrshad
Version: 0.4b0
Summary: A Python 3 module that contains all of my collections to let you code easier!
Home-page: https://github.com/mehrshaad/mehrshad-pypi
Author: Mehrshad Dadashzadeh
Author-email: mehrdadashzadeh1379@gmail.com
License: MIT
Download-URL: https://github.com/mehrshaad/mehrshad-pypi/archive/refs/tags/v0.4-beta.tar.gz
Keywords: mehrshad,json,excel,text
Platform: UNKNOWN
Classifier: Development Status :: 4 - Beta
Classifier: License :: OSI Approved :: MIT License
Classifier: Operating System :: OS Independent
Classifier: Programming Language :: Python :: 3
Requires-Python: >=3.4
